{
 "slug": "roof-drains-scuppers",
 "taxonomy": "services",
 "route": "/services/roof-drains-scuppers",
 "title": "Roof Drains and Scuppers in Spartanburg, SC | Commercial Roofers of Spartanburg",
 "metaDescription": "Roof drain and scupper repair, clearing, and retrofit for Spartanburg County flat and low-slope commercial roofs to reduce ponding-related membrane stress.",
 "internalLinks": [
  {
   "anchor": "Repairing What Upstate Thunderstorm Season Leaves Behind",
   "slug": "storm-damage-roof-repair",
   "taxonomy": "services",
   "href": "/services/storm-damage-roof-repair"
  },
  {
   "anchor": "TPO Membrane Systems for the Distribution and Supplier-Park Roofs Around Spartanburg",
   "slug": "tpo-single-ply-roofing",
   "taxonomy": "services",
   "href": "/services/tpo-single-ply-roofing"
  },
  {
   "anchor": "Acrylic Coatings for Well-Draining Roofs and Metal Panel Restoration",
   "slug": "acrylic-roof-coatings",
   "taxonomy": "services",
   "href": "/services/acrylic-roof-coatings"
  },
  {
   "anchor": "Built-Up Roof Systems on Spartanburg's Legacy Industrial Buildings",
   "slug": "built-up-roofing",
   "taxonomy": "services",
   "href": "/services/built-up-roofing"
  },
  {
   "anchor": "Full-System Reroofing for Spartanburg County's Manufacturing Base",
   "slug": "commercial-reroofing",
   "taxonomy": "services",
   "href": "/services/commercial-reroofing"
  },
  {
   "anchor": "Reroof Permitting Along Boiling Springs' SC-9 Retail Corridor",
   "slug": "boiling-springs",
   "taxonomy": "locations",
   "href": "/locations/boiling-springs"
  },
  {
   "anchor": "Roofing Refrigerated Warehouse and Cold Storage Buildings",
   "slug": "cold-storage-roofing",
   "taxonomy": "project-types",
   "href": "/project-types/cold-storage-roofing"
  },
  {
   "anchor": "Roof Service for the I-85 Distribution Corridor",
   "slug": "logistics-3pl",
   "taxonomy": "industries",
   "href": "/industries/logistics-3pl"
  }
 ],
 "html": "<h1>Drainage Problems Age a Roof Faster Than Almost Anything Else</h1>\n<p>Standing water on a flat or low-slope roof carries real cost beyond appearance. Ponding adds sustained weight, accelerates membrane wear at the water line, and gives UV and debris a place to concentrate their damage. Most drainage problems trace back to a clogged, undersized, or poorly located drain or scupper.</p>\n<h2>Why Ponding Happens Even on a Properly Sloped Roof</h2>\n<p>Every low-slope roof is built with some slope toward its drainage points, but that slope only works if the drains and scuppers themselves are clear and correctly sized. A single blocked internal drain can turn a well-designed roof into a standing water problem within one heavy rain event.</p>\n<p>Deck deflection over time, particularly on older steel-joist buildings, can also create low spots that weren't part of the original design. Where that's the case, adding a supplemental drain or scupper is often more practical than trying to correct the slope itself.</p>\n<p>We measure ponding depth and extent after a rain event rather than guessing from a dry roof walk, since a low spot that looks minor when dry can hold several inches of water after a heavy storm, adding real weight the structure wasn't necessarily sized to carry long term.</p>\n<h2>Internal Drains on Manufacturing and Warehouse Roofs</h2>\n<p>Large-footprint buildings along the I-85 corridor, including distribution centers and manufacturing plants measured in acres of roof area, typically rely on internal drain systems rather than perimeter scuppers, since the roof area is too large for edge drainage alone to keep up with a heavy storm.</p>\n<p>Internal drains need clear strainer baskets and unobstructed leader lines to function, and both are easy to overlook during routine maintenance since they're not visible from the roof surface. We check strainer condition and flow during every drainage service call, not only when a ponding complaint comes in.</p>\n<p>On the largest distribution roofs, a single leader line running to grade can carry a significant volume of water during a heavy storm, and a partial clog well below the roof surface can go unnoticed until the drain backs up. We check accessible cleanouts as part of the same visit where they exist.</p>\n<h2>Scuppers and Overflow Systems</h2>\n<p>Primary and overflow scuppers work as a pair: the primary drain handles normal rainfall, while the overflow scupper, set slightly higher, prevents catastrophic ponding if the primary system clogs or can't keep pace with an intense storm. A missing or blocked overflow scupper removes that safety margin entirely.</p>\n<p>On mill-era buildings that have had multiple roof modifications over the decades, we sometimes find overflow scuppers that were sealed over during a past recover and never reopened. We flag that during inspection since it's a code and drainage risk that's easy to miss without specifically checking for it.</p>\n<p>Restoring a sealed-over overflow scupper is usually a straightforward repair once identified, but the harder part is finding it in the first place, since a past recover crew may have covered it with membrane that matches the surrounding field almost exactly.</p>\n<h2>What Drainage Service Covers</h2>\n<ul>\n<li>Drain and scupper clearing of debris and sediment buildup</li>\n<li>Strainer basket inspection and leader line flow check</li>\n<li>Ponding area identification after a rain event</li>\n<li>Overflow scupper verification and code compliance check</li>\n<li>Drain retrofit or supplemental drain installation where needed</li>\n</ul>\n<h2>Seasonal Debris Load in the Upstate</h2>\n<p>Roofs near mature tree cover, common around older properties in the mill villages and downtown Spartanburg, see heavier leaf and debris accumulation in fall that can clog drains within a matter of weeks. Spring pollen load is a less obvious but real contributor, coating drain strainers with a fine sediment that reduces flow even without an obvious blockage.</p>\n<p>We time drainage clearing visits to catch both of those seasonal loads rather than relying on a single annual check.</p>\n<h2>When Retrofit Drainage Makes Sense</h2>\n<p>Where a roof consistently ponds in the same area despite clear drains and functioning scuppers, the fix is usually a retrofit: an additional drain, a tapered insulation crickets system to redirect flow, or both. We scope that work based on actual ponding patterns observed after rain, not assumptions from a dry-day roof walk. Where possible, we schedule a follow-up visit after the next significant rain to confirm the retrofit performed as designed before closing the project out.</p>\n<h2>Drainage Questions From Facilities Teams</h2>\n<h3>How often should roof drains be cleared?</h3>\n<p>At minimum twice a year, with additional checks after fall leaf drop or any storm event that could carry debris onto the roof.</p>\n<h3>Is standing water always a problem?</h3>\n<p>Brief ponding after a heavy rain that clears within a day or two is normal on many low-slope roofs. Water that sits for 48 hours or longer signals a drainage issue worth addressing.</p>\n<h3>What's the difference between a primary and overflow scupper?</h3>\n<p>The primary handles everyday rainfall, while the overflow, set higher, provides a backup path if the primary system can't keep up, preventing water from ponding to a dangerous depth.</p>\n<h3>Can a drain retrofit be added without a full reroof?</h3>\n<p>In many cases, yes, though it depends on the roof's construction and how the new drain needs to tie into the existing membrane and insulation.</p>\n<h3>Does ponding water void a roof warranty?</h3>\n<p>Many manufacturer warranties exclude damage caused by prolonged ponding, which is one reason we flag persistent ponding areas as a priority repair rather than treating them as a cosmetic issue that can wait.</p>",
 "image": "/images/services/roof-drains-scuppers-commercial-roofers-spartanburg-sc.webp"
}
