{"slug":"spray-polyurethane-foam","taxonomy":"roof-systems","route":"/roof-systems/spray-polyurethane-foam","title":"Spray Polyurethane Foam Roofing in Spartanburg, SC | Commercial Roofers of Spartanburg","metaDescription":"SPF roofing specification, insulation and slope-forming properties, and recoat cycles for irregular-shaped commercial roofs in Spartanburg County, SC.","internalLinks":[{"anchor":"60-Mil TPO Membrane Specification for Spartanburg Facilities","slug":"tpo-60-mil","taxonomy":"roof-systems","href":"/roof-systems/tpo-60-mil"},{"anchor":"Heavier-Gauge TPO for High-Traffic Industrial Roofs","slug":"tpo-80-mil","taxonomy":"roof-systems","href":"/roof-systems/tpo-80-mil"},{"anchor":"Black EPDM for Spartanburg's Older Industrial Buildings","slug":"epdm-black","taxonomy":"roof-systems","href":"/roof-systems/epdm-black"},{"anchor":"White EPDM as a Cooling-Load Alternative to Black Rubber","slug":"epdm-white","taxonomy":"roof-systems","href":"/roof-systems/epdm-white"},{"anchor":"SBS Modified Bitumen for Multi-Ply Roof Assemblies","slug":"modified-bitumen-sbs","taxonomy":"roof-systems","href":"/roof-systems/modified-bitumen-sbs"},{"anchor":"When a Recover Makes Sense on Spartanburg's Industrial Roofs","slug":"roof-recover-overlay","taxonomy":"services","href":"/services/roof-recover-overlay"},{"anchor":"Mill-Era Roofs Meeting New Construction Near Startex","slug":"startex","taxonomy":"locations","href":"/locations/startex"},{"anchor":"Roofing Occupied Apartment Communities Across the SC-9 Growth Corridor","slug":"multifamily-apartment-roofing","taxonomy":"project-types","href":"/project-types/multifamily-apartment-roofing"}],"html":"<h1>SPF: A Joint-Free, Slope-Forming System for Irregular Roofs</h1>\n<p>Spray polyurethane foam, or SPF, is the system we bring up when a Spartanburg County roof has an irregular shape, poor drainage geometry, or a substrate where seamed membrane systems create more transitions and detail work than the building justifies. It's fundamentally different from every other system on this site: SPF is sprayed in place, forms its own insulation and slope, and then gets a protective coating over the cured foam rather than being installed as a pre-manufactured sheet.</p>\n<h2>How SPF Roofing Actually Works</h2>\n<p>Two liquid components, an isocyanate and a polyol resin, are mixed and sprayed together, expanding on contact with the substrate to form a closed-cell foam that cures within seconds. That foam layer provides both insulation value and, because the applicator can vary spray thickness across the roof, the ability to build positive drainage slope into a roof that previously had none, correcting ponding water problems that are difficult to solve with a flat membrane system alone. Because the foam bonds directly and continuously to the substrate rather than being installed as discrete sheets, there are no field seams for water to find, which is a meaningful difference from every welded or taped membrane system covered elsewhere on this site.</p>\n<h2>Why Slope-Forming Matters on Older Buildings</h2>\n<p>A meaningful share of Spartanburg County's older mill and warehouse conversions were built with minimal or no designed roof slope, which creates chronic ponding that shortens the service life of whatever membrane sits on top. SPF's ability to add tapered insulation value directly through spray thickness, rather than requiring a separate tapered insulation board installation, is one of the main reasons we bring it into the conversation on buildings around Arcadia, Clifton, and other legacy mill sites with flat, aging roof decks. On some of these buildings the roof deck itself has settled unevenly over decades, and SPF's field-applied nature lets the crew correct for that unevenness in ways a factory-cut tapered board layout cannot always match precisely.</p>\n<h2>Protective Coating Requirements</h2>\n<p>Cured SPF is never left exposed. It requires a protective top coating, most commonly silicone or acrylic, applied at a manufacturer-specified thickness to protect the foam from UV degradation and mechanical damage. The coating is what actually weathers and needs periodic recoating over the life of the roof, while the underlying foam, if properly protected, can remain sound for decades. We treat the coating maintenance schedule as a defined, recurring line item in any SPF proposal rather than a one-time installation cost.</p>\n<h2>Application Conditions and Field Control</h2>\n<p>SPF application is highly sensitive to temperature, humidity, wind, and substrate moisture at the time of spraying, since the chemical reaction and cure quality depend on conditions matching the manufacturer's application window. Spartanburg's humid summer air and afternoon storm patterns narrow the practical application window on many projects, and we schedule SPF work around forecasted humidity and dew point conditions rather than treating it like membrane installation that tolerates a wider weather range.</p>\n<ul>\n<li>Confirm substrate moisture content is within spec before any foam application begins</li>\n<li>Vary spray thickness deliberately to correct ponding and build positive drainage slope</li>\n<li>Apply protective silicone or acrylic top coat at the manufacturer's specified thickness</li>\n<li>Schedule application around humidity and dew point windows in addition to temperature</li>\n<li>Establish a recurring recoat schedule as part of the long-term maintenance plan</li>\n<li>Inspect foam density and coating thickness with core samples on larger projects</li>\n</ul>\n<h2>FM and UL Ratings for SPF Assemblies</h2>\n<p>SPF roof assemblies carry FM 4470 wind uplift and UL 790 fire classification ratings tested with the specific foam density and coating system combination, similar to membrane assemblies. Foam density affects both structural and fire performance, so substituting a different foam formulation than what was tested can affect the assembly's rated status, which is why we source foam and coating from a single compatible manufacturer system rather than mixing components across suppliers.</p>\n<h2>Recoat Cycles and Long-Term Cost</h2>\n<p>SPF roofs are typically maintained on a recoat cycle, often in the 10 to 15 year range depending on coating type and UV exposure, rather than being torn off and replaced the way membrane systems eventually are. Over a multi-decade hold period, that recoat-based maintenance model can produce a lower total cost of ownership than repeated full membrane replacement, which is part of why SPF appeals to owners planning to hold industrial property long term rather than sell within a few years.</p>\n<h2>Questions on SPF Roofing</h2>\n<h3>Is SPF a good fit for every flat roof?</h3>\n<p>No. It works best on roofs with irregular geometry, drainage problems, or numerous penetrations where foam's ability to self-flash and self-slope adds real value. A simple rectangular roof with good existing drainage may not need SPF's added cost.</p>\n<h3>How often does SPF need to be recoated?</h3>\n<p>Recoat intervals commonly fall in the 10 to 15 year range depending on the coating system and sun exposure, though we set the actual schedule based on periodic inspection findings rather than a fixed calendar alone.</p>\n<h3>Can SPF be applied over an existing roof?</h3>\n<p>Often yes, provided the existing substrate is dry and structurally sound, which is one of SPF's advantages over membrane systems that more frequently require tear-off.</p>\n<h3>Does weather delay SPF projects more than membrane installation?</h3>\n<p>Yes. SPF application windows are narrower due to humidity and dew point sensitivity, so scheduling around Spartanburg's summer weather patterns takes more planning than membrane work.</p>\n<h3>Is SPF suitable for roofs with heavy foot traffic?</h3>\n<p>With the right coating system and, where needed, granule or walkway pad reinforcement, SPF can handle regular service traffic, though we plan reinforcement at known traffic paths during design rather than after installation.</p>","image":"/images/roof-systems/spray-polyurethane-foam-commercial-roofers-spartanburg-sc.webp"}